pycounts/__init__.py
pycounts/data/__init__.py
pycounts/data/flatland.txt
pycounts/datasets.py
pycounts/plotting.py
pycounts/pycounts.py
pycounts_labdmitriy-0.3.0.dist-info/LICENSE
pycounts_labdmitriy-0.3.0.dist-info/METADATA
pycounts_labdmitriy-0.3.0.dist-info/WHEEL
pycounts_labdmitriy-0.3.0.dist-info/RECORD
