Metadata-Version: 2.1
Name: pycounts-labdmitriy
Version: 0.3.0
Summary: Calculate word counts in a text file
License: MIT
Author: Dmitry Labazkin
Requires-Python: >=3.11
Classifier: License :: OSI Approved :: MIT License
Classifier: Programming Language :: Python :: 3
Classifier: Programming Language :: Python :: 3.11
Classifier: Programming Language :: Python :: 3.12
Classifier: Programming Language :: Python :: 3.13
Requires-Dist: matplotlib (>=3.9.2)
